dfembed-0.1.5.dist-info/METADATA
dfembed-0.1.5.dist-info/WHEEL
dfembed-0.1.5.dist-info/licenses/LICENSE
dfembed/__init__.py
dfembed/core.py
dfembed/dfembed.cp312-win_amd64.pyd
dfembed/llamaindex.py
dfembed-0.1.5.dist-info/RECORD
