Metadata-Version: 2.4
Name: dfembed
Version: 0.1.5
Requires-Dist: polars>=0.18.0
Requires-Dist: pyarrow>=11.0.0
Requires-Dist: pytest>=7.0.0 ; extra == 'test'
Provides-Extra: test
License-File: LICENSE
Summary: A Python library that embeds and indexes Arrow-based dataframes
Author-email: Alon Agmon <alon.agmon@gmail.com>
Requires-Python: >=3.8
